aiocflib/__init__.py
aiocflib/benchmarks/test_packet_sending.py
aiocflib/benchmarks/test_throughput.py
aiocflib/bootloader/__init__.py
aiocflib/bootloader/bootloader.py
aiocflib/bootloader/target.py
aiocflib/bootloader/types.py
aiocflib/crazyflie/__init__.py
aiocflib/crazyflie/app_channel.py
aiocflib/crazyflie/broadcast.py
aiocflib/crazyflie/commander.py
aiocflib/crazyflie/console.py
aiocflib/crazyflie/crazyflie.py
aiocflib/crazyflie/high_level_commander.py
aiocflib/crazyflie/led_ring.py
aiocflib/crazyflie/lighthouse.py
aiocflib/crazyflie/localization.py
aiocflib/crazyflie/log.py
aiocflib/crazyflie/mem.py
aiocflib/crazyflie/motors.py
aiocflib/crazyflie/param.py
aiocflib/crazyflie/platform.py
aiocflib/crtp/__init__.py
aiocflib/crtp/broadcaster.py
aiocflib/crtp/crtpstack.py
aiocflib/crtp/device.py
aiocflib/crtp/drivers/__init__.py
aiocflib/crtp/drivers/base.py
aiocflib/crtp/drivers/cpplink.py
aiocflib/crtp/drivers/radio.py
aiocflib/crtp/drivers/registry.py
aiocflib/crtp/drivers/sitl.py
aiocflib/crtp/drivers/usb.py
aiocflib/crtp/exceptions.py
aiocflib/crtp/middleware/__init__.py
aiocflib/crtp/middleware/base.py
aiocflib/crtp/middleware/log.py
aiocflib/crtp/middleware/registry.py
aiocflib/crtp/middleware/utils.py
aiocflib/crtp/strategies.py
aiocflib/drivers/__init__.py
aiocflib/drivers/cfusb.py
aiocflib/drivers/crazyradio.py
aiocflib/drivers/sitl.py
aiocflib/errors.py
aiocflib/utils/__init__.py
aiocflib/utils/addressing.py
aiocflib/utils/checksum.py
aiocflib/utils/chunks.py
aiocflib/utils/colors.py
aiocflib/utils/concurrency.py
aiocflib/utils/quaternion.py
aiocflib/utils/registry.py
aiocflib/utils/statistics.py
aiocflib/utils/timing.py
aiocflib/utils/toc.py
aiocflib/utils/typing.py
aiocflib/utils/usb.py
aiocflib/version.py
aiocflib-4.1.0.dist-info/LICENSE.txt
aiocflib-4.1.0.dist-info/METADATA
aiocflib-4.1.0.dist-info/WHEEL
aiocflib-4.1.0.dist-info/RECORD
