Metadata-Version: 2.1
Name: aiocflib
Version: 4.1.0
Summary: Python async API for Crazyflie drones
License: GPL-3.0-or-later
Author: Tamas Nepusz
Author-email: tamas@collmot.com
Requires-Python: >=3.8,<4.0
Classifier: License :: OSI Approved :: GNU General Public License v3 or later (GPLv3+)
Classifier: Programming Language :: Python :: 3
Classifier: Programming Language :: Python :: 3.8
Classifier: Programming Language :: Python :: 3.9
Classifier: Programming Language :: Python :: 3.10
Classifier: Programming Language :: Python :: 3.11
Classifier: Programming Language :: Python :: 3.12
Classifier: Programming Language :: Python :: 3.13
Requires-Dist: anyio (>=4.1.0,<5.0.0)
Requires-Dist: colorama (>=0.4.6,<0.5.0)
Requires-Dist: colour (>=0.1.5,<0.2.0)
Requires-Dist: exceptiongroup (>=1.2.0,<2.0.0) ; python_version < "3.11"
Requires-Dist: hexdump (>=3.3,<4.0)
Requires-Dist: outcome (>=1.3.0.post0,<2.0.0)
Requires-Dist: pyusb (>=1.2.1,<2.0.0)
